nb_js_diagrammers/__init__.py
nb_js_diagrammers/flowchartjs.py
nb_js_diagrammers/magics.py
nb_js_diagrammers/mermaid.py
nb_js_diagrammers/wavedrom.py
nb_js_diagrammers/wavesurfer.py
nb_js_diagrammers-0.0.9.dist-info/LICENSE
nb_js_diagrammers-0.0.9.dist-info/METADATA
nb_js_diagrammers-0.0.9.dist-info/WHEEL
nb_js_diagrammers-0.0.9.dist-info/top_level.txt
nb_js_diagrammers-0.0.9.dist-info/RECORD
