Metadata-Version: 2.1
Name: nb-js-diagrammers
Version: 0.0.9
Summary: Javascript diagrammers and magics for IPython and Jupyter notebooks
Home-page: https://github.com/innovationOUtside/nb_js_diagrammers
Author: Tony Hirst
Author-email: tony.hirst@open.ac.uk
License: MIT
License-File: LICENSE
Requires-Dist: pyflowchart
